envparse2/__init__.py
envparse2-1.0.0.dist-info/METADATA
envparse2-1.0.0.dist-info/WHEEL
envparse2-1.0.0.dist-info/licenses/LICENSE
envparse2-1.0.0.dist-info/RECORD
