Metadata-Version: 2.4
Name: envparse2
Version: 1.0.0
Summary: Simple environment variable parsing
Project-URL: Repository, https://github.com/beregond/envparse2
Author-email: Rick Harris <rconradharris@gmail.com>
Maintainer-email: Szczepan Cieślik <szczepan.cieslik@gmail.com>
License-Expression: MIT
License-File: LICENSE
Classifier: Programming Language :: Python :: 3.9
Classifier: Programming Language :: Python :: 3.10
Classifier: Programming Language :: Python :: 3.11
Classifier: Programming Language :: Python :: 3.12
Classifier: Programming Language :: Python :: 3.13
